service_account_auth/__init__.py
service_account_auth/authorized_service.py
service_account_auth/version.py
gclient_service_account_auth-0.3.0.dist-info/LICENSE
gclient_service_account_auth-0.3.0.dist-info/METADATA
gclient_service_account_auth-0.3.0.dist-info/WHEEL
gclient_service_account_auth-0.3.0.dist-info/top_level.txt
gclient_service_account_auth-0.3.0.dist-info/RECORD
