Metadata-Version: 2.1
Name: gclient-service-account-auth
Version: 0.3.0
Summary: Easily create an authorized service-object for interacting with google's client APIs, server to server.
Home-page: http://github.com/ambitioninc/gclient-service-account-auth
Author: Erik Swanson
Author-email: TheErikSwanson@gmail.com
License: MIT
Platform: UNKNOWN
Classifier: Programming Language :: Python
Classifier: Intended Audience :: Developers
Classifier: License :: OSI Approved :: MIT License
Classifier: Operating System :: OS Independent
Requires-Dist: httplib2 (>=0.9)
Requires-Dist: google-api-python-client (~=1.4)
Requires-Dist: pyopenssl (>=0.14)
